pyapiepo/__init__.py
pyapiepo/main.py
pyapiepo-1.1.4.dist-info/METADATA
pyapiepo-1.1.4.dist-info/WHEEL
pyapiepo-1.1.4.dist-info/top_level.txt
pyapiepo-1.1.4.dist-info/RECORD
